MANIFEST.in
README
requirements.txt
setup.py
ajenti.plugin.augeas.egg-info/PKG-INFO
ajenti.plugin.augeas.egg-info/SOURCES.txt
ajenti.plugin.augeas.egg-info/dependency_links.txt
ajenti.plugin.augeas.egg-info/requires.txt
ajenti.plugin.augeas.egg-info/top_level.txt
ajenti_plugin_augeas/README.md
ajenti_plugin_augeas/__init__.py
ajenti_plugin_augeas/api.py
ajenti_plugin_augeas/plugin.yml
ajenti_plugin_augeas/requirements.txt
ajenti_plugin_augeas/views.py
ajenti_plugin_augeas/locale/app.pot
ajenti_plugin_augeas/locale/af/LC_MESSAGES/app.js
ajenti_plugin_augeas/locale/af/LC_MESSAGES/app.po
ajenti_plugin_augeas/locale/af/LC_MESSAGES/app.po~
ajenti_plugin_augeas/locale/ar/LC_MESSAGES/app.js
ajenti_plugin_augeas/locale/ar/LC_MESSAGES/app.po
ajenti_plugin_augeas/locale/ar/LC_MESSAGES/app.po~
ajenti_plugin_augeas/locale/be/LC_MESSAGES/app.js
ajenti_plugin_augeas/locale/be/LC_MESSAGES/app.po
ajenti_plugin_augeas/locale/be/LC_MESSAGES/app.po~
ajenti_plugin_augeas/locale/bg/LC_MESSAGES/app.js
ajenti_plugin_augeas/locale/bg/LC_MESSAGES/app.po
ajenti_plugin_augeas/locale/bg/LC_MESSAGES/app.po~
ajenti_plugin_augeas/locale/bn/LC_MESSAGES/app.js
ajenti_plugin_augeas/locale/bn/LC_MESSAGES/app.po
ajenti_plugin_augeas/locale/bn/LC_MESSAGES/app.po~
ajenti_plugin_augeas/locale/bs/LC_MESSAGES/app.js
ajenti_plugin_augeas/locale/bs/LC_MESSAGES/app.po
ajenti_plugin_augeas/locale/ca/LC_MESSAGES/app.js
ajenti_plugin_augeas/locale/ca/LC_MESSAGES/app.po
ajenti_plugin_augeas/locale/ca/LC_MESSAGES/app.po~
ajenti_plugin_augeas/locale/cs/LC_MESSAGES/app.js
ajenti_plugin_augeas/locale/cs/LC_MESSAGES/app.po
ajenti_plugin_augeas/locale/cs/LC_MESSAGES/app.po~
ajenti_plugin_augeas/locale/da/LC_MESSAGES/app.js
ajenti_plugin_augeas/locale/da/LC_MESSAGES/app.po
ajenti_plugin_augeas/locale/da/LC_MESSAGES/app.po~
ajenti_plugin_augeas/locale/de/LC_MESSAGES/app.js
ajenti_plugin_augeas/locale/de/LC_MESSAGES/app.po
ajenti_plugin_augeas/locale/de/LC_MESSAGES/app.po~
ajenti_plugin_augeas/locale/el/LC_MESSAGES/app.js
ajenti_plugin_augeas/locale/el/LC_MESSAGES/app.po
ajenti_plugin_augeas/locale/el/LC_MESSAGES/app.po~
ajenti_plugin_augeas/locale/en/LC_MESSAGES/app.po
ajenti_plugin_augeas/locale/eo/LC_MESSAGES/app.js
