Metadata-Version: 1.2
Name: ajenti.plugin.augeas
Version: 0.20
Summary: Augeas API
Home-page: https://ajenti.org
Author: Ajenti project
Author-email: e@ajenti.org
License: UNKNOWN
Platform: UNKNOWN
Requires-Python: >=3
